ahqapiclient/__init__.py
ahqapiclient/http_client.py
ahqapiclient/resources/__init__.py
ahqapiclient/resources/action.py
ahqapiclient/resources/aggregation.py
ahqapiclient/resources/backendsettings.py
ahqapiclient/resources/case.py
ahqapiclient/resources/client.py
ahqapiclient/resources/endpoint.py
ahqapiclient/resources/escalation.py
ahqapiclient/resources/inbound_filter.py
ahqapiclient/resources/incident.py
ahqapiclient/resources/log.py
ahqapiclient/resources/mailbox.py
ahqapiclient/resources/me.py
ahqapiclient/resources/network.py
ahqapiclient/resources/noop.py
ahqapiclient/resources/setting.py
ahqapiclient/resources/system.py
ahqapiclient/resources/user.py
ahqapiclient-0.6.1.dist-info/DESCRIPTION.rst
ahqapiclient-0.6.1.dist-info/METADATA
ahqapiclient-0.6.1.dist-info/RECORD
ahqapiclient-0.6.1.dist-info/WHEEL
ahqapiclient-0.6.1.dist-info/metadata.json
ahqapiclient-0.6.1.dist-info/top_level.txt
