Metadata-Version: 2.0
Name: ahqapiclient
Version: 0.6.1
Summary: AbuseHQ API Client
Home-page: https://www.abusix.com/
Author: Frederik Petersen
Author-email: fp@abusix.com
License: UNKNOWN
Keywords: abusehq api client
Platform: UNKNOWN
Classifier: Intended Audience :: Developers
Classifier: Programming Language :: Python
Classifier: Programming Language :: Python :: 2.6
Classifier: Programming Language :: Python :: 2.7
Classifier: Topic :: Internet :: WWW/HTTP
Requires-Dist: requests
Requires-Dist: ujson
